SSubdomains/__init__.py
SSubdomains/admin.py
SSubdomains/apps.py
SSubdomains/config.py
SSubdomains/domain.py
SSubdomains/views.py
SSubdomains/middleware/__init__.py
SSubdomains/middleware/handler.py
SSubdomains/middleware/subdaomains_manager.py
SSubdomains/migrations/0001_initial.py
SSubdomains/migrations/0002_alter_subdomain_excluded_by_groups_and_more.py
SSubdomains/migrations/__init__.py
SSubdomains/models/__init__.py
SSubdomains/models/subdomain.py
SSubdomains/models/subdomain_manager.py
SSubdomains/utilities/domain_handler.py
SSubdomains/utilities/ip_checker.py
SSubdomains-0.0.8b0.dist-info/LICENSE
SSubdomains-0.0.8b0.dist-info/METADATA
SSubdomains-0.0.8b0.dist-info/WHEEL
SSubdomains-0.0.8b0.dist-info/top_level.txt
SSubdomains-0.0.8b0.dist-info/RECORD
