Metadata-Version: 2.1
Name: SSubdomains
Version: 0.0.8b0
Summary: SSubdomain provides a clean way to manage multiple subdomains in a Django project. User role-based access control makes it easy to restrict parts of a site.
Author-email: Salah aldain alhajj <contact@salahaldain.com>
Project-URL: Homepage, https://github.com/salah-alhajj/SSubdomains
Project-URL: Issues, https://github.com/salah-alhajj/SSubdomains/issues
Classifier: Programming Language :: Python :: 3
Classifier: License :: OSI Approved :: MIT License
Classifier: Operating System :: OS Independent
Requires-Python: >=3.8
License-File: LICENSE
